text_vectorify/__init__.py
text_vectorify/__main__.py
text_vectorify/factory.py
text_vectorify/main.py
text_vectorify/vectorify.py
text_vectorify/embedders/__init__.py
text_vectorify/embedders/base.py
text_vectorify/embedders/bge.py
text_vectorify/embedders/huggingface.py
text_vectorify/embedders/m3e.py
text_vectorify/embedders/multi_layer.py
text_vectorify/embedders/openai.py
text_vectorify/embedders/sentence_bert.py
text_vectorify/embedders/tfidf.py
text_vectorify/embedders/topic.py
text_vectorify-1.2.0.dist-info/licenses/LICENSE
text_vectorify-1.2.0.dist-info/METADATA
text_vectorify-1.2.0.dist-info/WHEEL
text_vectorify-1.2.0.dist-info/entry_points.txt
text_vectorify-1.2.0.dist-info/top_level.txt
text_vectorify-1.2.0.dist-info/RECORD
