Metadata-Version: 2.4
Name: text-vectorify
Version: 1.2.0
Summary: A powerful and flexible Python tool for text vectorization with multiple embedding models
Home-page: https://github.com/changyy/py-text-vectorify
Author: changyy
Author-email: changyy.csie@gmail.com
Classifier: Development Status :: 4 - Beta
Classifier: Intended Audience :: Developers
Classifier: Intended Audience :: Science/Research
Classifier: License :: OSI Approved :: MIT License
Classifier: Operating System :: OS Independent
Classifier: Programming Language :: Python :: 3
Classifier: Programming Language :: Python :: 3.8
Classifier: Programming Language :: Python :: 3.9
Classifier: Programming Language :: Python :: 3.10
Classifier: Programming Language :: Python :: 3.11
Classifier: Programming Language :: Python :: 3.12
Classifier: Topic :: Scientific/Engineering :: Artificial Intelligence
Classifier: Topic :: Text Processing :: Linguistic
Requires-Python: >=3.8
License-File: LICENSE
Requires-Dist: numpy>=1.21.0
Requires-Dist: scikit-learn>=1.0.0
Requires-Dist: spacy>=3.4.0
Provides-Extra: openai
Requires-Dist: openai>=1.0.0; extra == "openai"
Provides-Extra: transformers
Requires-Dist: sentence-transformers>=2.0.0; extra == "transformers"
Requires-Dist: transformers>=4.0.0; extra == "transformers"
Requires-Dist: torch>=1.9.0; extra == "transformers"
Provides-Extra: advanced
Requires-Dist: bertopic>=0.14.0; extra == "advanced"
Requires-Dist: jieba>=0.42.0; extra == "advanced"
Requires-Dist: pkuseg>=0.0.25; extra == "advanced"
Requires-Dist: umap-learn>=0.5.0; extra == "advanced"
Provides-Extra: dev
Requires-Dist: pytest>=6.0.0; extra == "dev"
Requires-Dist: pytest-cov>=2.0.0; extra == "dev"
Requires-Dist: black>=21.0.0; extra == "dev"
Requires-Dist: flake8>=3.9.0; extra == "dev"
Requires-Dist: mypy>=0.900; extra == "dev"
Requires-Dist: isort>=5.0.0; extra == "dev"
Provides-Extra: all
Requires-Dist: openai>=1.0.0; extra == "all"
Requires-Dist: sentence-transformers>=2.0.0; extra == "all"
Requires-Dist: transformers>=4.0.0; extra == "all"
Requires-Dist: torch>=1.9.0; extra == "all"
Requires-Dist: bertopic>=0.14.0; extra == "all"
Requires-Dist: jieba>=0.42.0; extra == "all"
Requires-Dist: pkuseg>=0.0.25; extra == "all"
Requires-Dist: umap-learn>=0.5.0; extra == "all"
Dynamic: author
Dynamic: author-email
Dynamic: classifier
Dynamic: description
Dynamic: description-content-type
Dynamic: home-page
Dynamic: license-file
Dynamic: provides-extra
Dynamic: requires-dist
Dynamic: requires-python
Dynamic: summary
